{"type":"FeatureCollection","features":[{"type":"Feature","geometry":{"type":"Point","coordinates":[6.083887,50.775346]},"properties":{"name":"Aachen, Germany","continent":null,"country":"Germany","province":"North Rhine-Westphalia","region":null,"city":"AC"}}]}