{"type":"FeatureCollection","features":[{"type":"Feature","geometry":{"type":"Point","coordinates":[-36.781951,-9.571306]},"properties":{"name":"Alagoas, Brazil","continent":null,"country":"Brazil","province":"State of Alagoas","region":null,"city":null}}]}