{"type":"FeatureCollection","features":[{"type":"Feature","geometry":{"type":"Point","coordinates":[-116.576504,53.933271]},"properties":{"name":"Alberta, Canada","continent":null,"country":"Canada","province":"Alberta","region":null,"city":null}}]}