{"type":"FeatureCollection","features":[{"type":"Feature","geometry":{"type":"Point","coordinates":[2.258826,22.830391]},"properties":{"name":"Algeria","continent":null,"country":"RADP","province":null,"region":null,"city":null}}]}