{"type":"FeatureCollection","features":[{"type":"Feature","geometry":{"type":"Point","coordinates":[6.237595,44.077872]},"properties":{"name":"Alpes-de-Haute-Provence, France","continent":null,"country":"France","province":"Provence-Alpes-Côte d'Azur","region":null,"city":null}}]}