{"type":"FeatureCollection","features":[{"type":"Feature","geometry":{"type":"Point","coordinates":[-76.612189,39.290385]},"properties":{"name":"Baltimore, MD","continent":null,"country":"United States","province":"Maryland","region":null,"city":"Baltimore"}}]}