{"type":"FeatureCollection","features":[{"type":"Feature","geometry":{"type":"Point","coordinates":[17.679076,43.915886]},"properties":{"name":"Bosnia and Herzegovina","continent":null,"country":"Bosnia and Herzegovina","province":null,"region":null,"city":null}}]}