{"type":"FeatureCollection","features":[{"type":"Feature","geometry":{"type":"Point","coordinates":[-51.92528,-14.235004]},"properties":{"name":"Brazil","continent":null,"country":"Brazil","province":null,"region":null,"city":null}}]}