{"type":"FeatureCollection","features":[{"type":"Feature","geometry":{"type":"Point","coordinates":[-80.843127,35.227087]},"properties":{"name":"Charlotte, NC","continent":null,"country":"United States","province":"North Carolina","region":null,"city":"Charlotte"}}]}