{"type":"FeatureCollection","features":[{"type":"Feature","geometry":{"type":"Point","coordinates":[-2.218593,53.161045]},"properties":{"name":"Cheshire East, UK","continent":null,"country":"United Kingdoms","province":"England","region":"Cheshire East","city":null}}]}