{"type":"FeatureCollection","features":[{"type":"Feature","geometry":{"type":"Point","coordinates":[-87.629798,41.878114]},"properties":{"name":"Chicago, IL","continent":null,"country":"United States","province":"Illinois","region":null,"city":"Chicago"}}]}