{"type":"FeatureCollection","features":[{"type":"Feature","geometry":{"type":"Point","coordinates":[6.960279,50.937531]},"properties":{"name":"Cologne, Germany","continent":null,"country":"Germany","province":"North Rhine-Westphalia","region":null,"city":"Cologne"}}]}