{"type":"FeatureCollection","features":[{"type":"Feature","geometry":{"type":"Point","coordinates":[-105.782067,39.550051]},"properties":{"name":"Colorado","continent":null,"country":"United States","province":"Colorado","region":null,"city":null}}]}