{"type":"FeatureCollection","features":[{"type":"Feature","geometry":{"type":"Point","coordinates":[9.957113,56.98966]},"properties":{"name":"Denmark","continent":null,"country":"Danmark","province":null,"region":null,"city":null}}]}