{"type":"FeatureCollection","features":[{"type":"Feature","geometry":{"type":"Point","coordinates":[-78.898619,35.994033]},"properties":{"name":"Durham, NC","continent":null,"country":"United States","province":"North Carolina","region":null,"city":"Durham"}}]}