{"type":"FeatureCollection","features":[{"type":"Feature","geometry":{"type":"Point","coordinates":[34.976418,31.412341]},"properties":{"name":"Gaza Strip","continent":null,"country":"الأراضي الفلسطينية","province":null,"region":null,"city":null}}]}