{"type":"FeatureCollection","features":[{"type":"Feature","geometry":{"type":"Point","coordinates":[2.272888,41.588773]},"properties":{"name":"Granollers, Spain","continent":null,"country":"Spain","province":"Catalonia","region":null,"city":"Granollers"}}]}