{"type":"FeatureCollection","features":[{"type":"Feature","geometry":{"type":"Point","coordinates":[9.993682,53.551085]},"properties":{"name":"Hamburg, Germany","continent":null,"country":"Germany","province":"Hamburg","region":null,"city":"Hamburg"}}]}