{"type":"FeatureCollection","features":[{"type":"Feature","geometry":{"type":"Point","coordinates":[2.218807,48.828508]},"properties":{"name":"Hauts-de-Seine, France","continent":null,"country":"France","province":"Île-de-France","region":null,"city":null}}]}