{"type":"FeatureCollection","features":[{"type":"Feature","geometry":{"type":"Point","coordinates":[-155.582782,19.896766]},"properties":{"name":"Hawaii","continent":null,"country":"United States","province":"Hawaii","region":null,"city":null}}]}