{"type":"FeatureCollection","features":[{"type":"Feature","geometry":{"type":"Point","coordinates":[-93.097702,41.878003]},"properties":{"name":"Iowa","continent":null,"country":"United States","province":"Iowa","region":null,"city":null}}]}