{"type":"FeatureCollection","features":[{"type":"Feature","geometry":{"type":"Point","coordinates":[37.906193,-0.023559]},"properties":{"name":"Kenya","continent":null,"country":"Kenya","province":null,"region":null,"city":null}}]}