{"type":"FeatureCollection","features":[{"type":"Feature","geometry":{"type":"Point","coordinates":[-118.24366,34.052227]},"properties":{"name":"Los Angeles County, CA","continent":null,"country":"United States","province":"California","region":"Los Angeles County","city":null}}]}