{"type":"FeatureCollection","features":[{"type":"Feature","geometry":{"type":"Point","coordinates":[-76.641271,39.045755]},"properties":{"name":"Maryland","continent":null,"country":"United States","province":"Maryland","region":null,"city":null}}]}