{"type":"FeatureCollection","features":[{"type":"Feature","geometry":{"type":"Point","coordinates":[-110.362566,46.879682]},"properties":{"name":"Montana","continent":null,"country":"United States","province":"Montana","region":null,"city":null}}]}