{"type":"FeatureCollection","features":[{"type":"Feature","geometry":{"type":"Point","coordinates":[5.534607,52.237989]},"properties":{"name":"Netherlands","continent":null,"country":"Netherlands","province":null,"region":null,"city":null}}]}