{"type":"FeatureCollection","features":[{"type":"Feature","geometry":{"type":"Point","coordinates":[-74.005941,40.712784]},"properties":{"name":"New York, NY","continent":null,"country":"United States","province":"New York","region":null,"city":"New York"}}]}