{"type":"FeatureCollection","features":[{"type":"Feature","geometry":{"type":"Point","coordinates":[-75.697193,45.42153]},"properties":{"name":"Ottawa, Canada","continent":null,"country":"Canada","province":"Ontario","region":null,"city":"Ottawa"}}]}