{"type":"FeatureCollection","features":[{"type":"Feature","geometry":{"type":"Point","coordinates":[-58.443832,-23.442503]},"properties":{"name":"Paraguay","continent":null,"country":"Paraguay","province":null,"region":null,"city":null}}]}