{"type":"FeatureCollection","features":[{"type":"Feature","geometry":{"type":"Point","coordinates":[2.324468,50.573277]},"properties":{"name":"Pas-de-Calais, France","continent":null,"country":"France","province":"Hauts-de-France","region":null,"city":null}}]}