{"type":"FeatureCollection","features":[{"type":"Feature","geometry":{"type":"Point","coordinates":[-8.349015,38.917386]},"properties":{"name":"Portugal","continent":null,"country":"Portugal","province":null,"region":null,"city":null}}]}