{"type":"FeatureCollection","features":[{"type":"Feature","geometry":{"type":"Point","coordinates":[-71.412834,41.823989]},"properties":{"name":"Providence, RI","continent":null,"country":"United States","province":"Rhode Island","region":null,"city":"Providence"}}]}