{"type":"FeatureCollection","features":[{"type":"Feature","geometry":{"type":"Point","coordinates":[7.308953,50.118346]},"properties":{"name":"Rheinland-Pfalz, Germany","continent":null,"country":"Germany","province":"Rhineland-Palatinate","region":null,"city":null}}]}