{"type":"FeatureCollection","features":[{"type":"Feature","geometry":{"type":"Point","coordinates":[-51.217699,-30.034632]},"properties":{"name":"Rio Grande do Sul, Brazil","continent":null,"country":"Brazil","province":"State of Rio Grande do Sul","region":null,"city":null}}]}