{"type":"FeatureCollection","features":[{"type":"Feature","geometry":{"type":"Point","coordinates":[-117.396119,33.953297]},"properties":{"name":"Riverside County, CA","continent":null,"country":"United States","province":"California","region":"Riverside County","city":null}}]}