{"type":"FeatureCollection","features":[{"type":"Feature","geometry":{"type":"Point","coordinates":[-121.288006,38.752124]},"properties":{"name":"Roseville, CA","continent":null,"country":"United States","province":"California","region":null,"city":"Roseville"}}]}