{"type":"FeatureCollection","features":[{"type":"Feature","geometry":{"type":"Point","coordinates":[105.318756,61.52401]},"properties":{"name":"Russia","continent":null,"country":"Russia","province":null,"region":null,"city":null}}]}