{"type":"FeatureCollection","features":[{"type":"Feature","geometry":{"type":"Point","coordinates":[-121.4944,38.581572]},"properties":{"name":"Sacramento, CA","continent":null,"country":"United States of America","province":"California","region":null,"city":"Sacramento"}}]}