{"type":"FeatureCollection","features":[{"type":"Feature","geometry":{"type":"Point","coordinates":[-93.089958,44.953703]},"properties":{"name":"Saint Paul, MI","continent":null,"country":"United States","province":"Michigan","region":null,"city":"Idlewild"}}]}