{"type":"FeatureCollection","features":[{"type":"Feature","geometry":{"type":"Point","coordinates":[-2.025674,48.649337]},"properties":{"name":"Saint-Malo, France","continent":null,"country":"France","province":"Brittany","region":null,"city":"St-Malo"}}]}