{"type":"FeatureCollection","features":[{"type":"Feature","geometry":{"type":"Point","coordinates":[13.986256,53.413685]},"properties":{"name":"Schonfeld, Germany","continent":null,"country":"Germany","province":"Brandenburg","region":null,"city":"Schönfeld"}}]}