{"type":"FeatureCollection","features":[{"type":"Feature","geometry":{"type":"Point","coordinates":[22.937506,-30.559482]},"properties":{"name":"South Africa","continent":null,"country":"South Africa","province":null,"region":null,"city":null}}]}