{"type":"FeatureCollection","features":[{"type":"Feature","geometry":{"type":"Point","coordinates":[-55.605243,4.05018]},"properties":{"name":"Suriname","continent":null,"country":"Suriname","province":null,"region":null,"city":null}}]}