{"type":"FeatureCollection","features":[{"type":"Feature","geometry":{"type":"Point","coordinates":[-111.093731,39.32098]},"properties":{"name":"Utah","continent":null,"country":"United States","province":"Utah","region":null,"city":null}}]}