{"type":"FeatureCollection","features":[{"type":"Feature","geometry":{"type":"Point","coordinates":[-72.577841,44.558803]},"properties":{"name":"Vermont","continent":null,"country":"United States","province":"Vermont","region":null,"city":null}}]}