{"type":"FeatureCollection","features":[{"type":"Feature","geometry":{"type":"Point","coordinates":[144.785153,-37.471308]},"properties":{"name":"Victoria, Australia","continent":null,"country":"Australia","province":"Victoria","region":null,"city":null}}]}