{"type":"FeatureCollection","features":[{"type":"Feature","geometry":{"type":"Point","coordinates":[4.451007,50.417564]},"properties":{"name":"Walloon, Belgium","continent":null,"country":"Belgium","province":"Walloon Region","region":null,"city":null}}]}