{"type":"FeatureCollection","features":[{"type":"Feature","geometry":{"type":"Point","coordinates":[-77.036871,38.907192]},"properties":{"name":"Washington DC","continent":null,"country":"United States","province":"District of Columbia","region":null,"city":"Washington"}}]}