{"type":"FeatureCollection","features":[{"type":"Feature","geometry":{"type":"Point","coordinates":[-121.530234,38.580461]},"properties":{"name":"West Sacramento, CA","continent":null,"country":"United States","province":"California","region":null,"city":"West Sacramento"}}]}