{"type":"FeatureCollection","features":[{"type":"Feature","geometry":{"type":"Point","coordinates":[-83.036363,42.314937]},"properties":{"name":"Windsor, Canada","continent":null,"country":"Canada","province":"Ontario","region":null,"city":"Windsor"}}]}