{"type":"FeatureCollection","features":[{"type":"Feature","geometry":{"type":"Point","coordinates":[15.981919,45.815011]},"properties":{"name":"Zagreb, Croatia","continent":null,"country":"Croatia","province":"City of Zagreb","region":null,"city":"Zagreb"}}]}